random_survival_forest/__init__.py
random_survival_forest/models.py
random_survival_forest/scoring.py
random_survival_forest/splitting.py
random_survival_forest-0.8.2.dist-info/LICENSE.txt
random_survival_forest-0.8.2.dist-info/METADATA
random_survival_forest-0.8.2.dist-info/WHEEL
random_survival_forest-0.8.2.dist-info/top_level.txt
random_survival_forest-0.8.2.dist-info/RECORD
