Metadata-Version: 2.1
Name: random_survival_forest
Version: 0.8.2
Summary: A Random Survival Forest implementation inspired by Ishwaran et al.
Home-page: https://github.com/julianspaeth/random-survival-forest
Download-URL: https://github.com/julianspaeth/random-survival-forest/archive/v0.1-beta.tar.gz
Author: Julian Späth
Author-email: spaethju@posteo.de
License: MIT License
Keywords: survival-analysis,survival-prediction,machine-learning,random-forest,random-survival-forest
Classifier: Development Status :: 4 - Beta
Classifier: Topic :: Software Development :: Build Tools
Classifier: License :: OSI Approved :: MIT License
Classifier: Programming Language :: Python :: 3.8
Classifier: Programming Language :: Python :: 3.9
Classifier: Programming Language :: Python :: 3.10
License-File: LICENSE.txt
Requires-Dist: numpy
Requires-Dist: pandas
Requires-Dist: joblib
Requires-Dist: multiprocess
Requires-Dist: lifelines
Requires-Dist: scikit-learn
